ImageReward/ImageReward.py
ImageReward/ReFL.py
ImageReward/__init__.py
ImageReward/utils.py
ImageReward/models/AestheticScore.py
ImageReward/models/BLIPScore.py
ImageReward/models/CLIPScore.py
ImageReward/models/__init__.py
ImageReward/models/BLIP/__init__.py
ImageReward/models/BLIP/blip.py
ImageReward/models/BLIP/blip_pretrain.py
ImageReward/models/BLIP/med.py
ImageReward/models/BLIP/vit.py
image_reward-1.5.dist-info/LICENSE
image_reward-1.5.dist-info/METADATA
image_reward-1.5.dist-info/WHEEL
image_reward-1.5.dist-info/dependency_links.txt
image_reward-1.5.dist-info/top_level.txt
image_reward-1.5.dist-info/RECORD
