Metadata-Version: 2.1
Name: image-reward
Version: 1.5
Summary: ImageReward
Home-page: https://github.com/THUDM/ImageReward
Author: Jiazheng Xu, et al.
Author-email: <xjz22@mails.tsinghua.edu.cn>
License: Apache 2.0 license
Requires-Python: >=3.5
License-File: LICENSE
Requires-Dist: timm (==0.6.13)
Requires-Dist: transformers (>=4.27.4)
Requires-Dist: fairscale (==0.4.13)
Requires-Dist: huggingface-hub (>=0.13.4)
Requires-Dist: diffusers (>=0.16.0)
Requires-Dist: accelerate (>=0.16.0)
Requires-Dist: datasets (>=2.11.0)
